{
    "status": "0",
    "msg": {
        "result": [
            {
                "iVideoId": "120116",
                "iType": "616",
                "iSubType": "636",
                "sAuthor": "TGL",
                "iFrom": "1",
                "sTitle": "大招支援进场就是屠杀 哪吒精彩操作秀",
                "sDesc": "兰陵王隐身开大就是要打你个措手不及；娜可露露爆炸输出玩鹰的少女就是彪悍；用着无惧虞姬双枪劲射不怂就是刚；实力乱秀马可波罗就是这么酷炫；大招支援进场就是屠杀哪吒",
                "sUrl": "",
                "sIMG": "//itea-cdn.qq.com/file/tgl/20170417/1.1492368220.jpg",
                "iTime": "03:09",
                "iTotalPlay": "5558",
                "iMark": "0",
                "sExt1": "898,948,895,1240,2017",
                "sExt2": "",
                "sExt3": "",
                "sIdxTime": "2017-04-17 14:36:20",
                "sCreated": "2017-04-17 14:36:20",
                "iBiz": "18"
            },
            {
                "iVideoId": "120117",
                "iType": "616",
                "iSubType": "636",
                "sAuthor": "TGL",
                "iFrom": "1",
                "sTitle": "骚气走位移动炮台 黄忠击杀英雄秀",
                "sDesc": "嬴政灵活走位拼死三杀；韩信镇守水晶威力爆发取三杀；潇洒走位灵活收割马可波罗；杨戬王者峡谷实力乱秀疯狂屠杀；骚气走位移动炮台黄忠",
                "sUrl": "",
                "sIMG": "//itea-cdn.qq.com/file/tgl/20170417/3.1492368331.jpg",
                "iTime": "03:05",
                "iTotalPlay": "9653",
                "iMark": "0",
                "sExt1": "599,618,1240,1638,2027",
                "sExt2": "",
                "sExt3": "",
                "sIdxTime": "2017-04-17 14:34:36",
                "sCreated": "2017-04-17 14:34:36",
                "iBiz": "18"
            },
            {
                "iVideoId": "120118",
                "iType": "616",
                "iSubType": "636",
                "sAuthor": "TGL",
                "iFrom": "1",
                "sTitle": "大圣发威秒天秒地势不可挡 孙悟空击杀秀",
                "sDesc": "兰陵王隐身开大显身瞬秒对手；暴脾气娜可露露突脸硬刚拼死三杀；成吉思汗无坚不摧屠杀实力秀；双枪虞姬爆炸输出收残血看谁还敢浪；大圣发威秒天秒地势不可挡孙悟空",
                "sUrl": "",
                "sIMG": "//itea-cdn.qq.com/file/tgl/20170417/2.1492368448.jpg",
                "iTime": "03:07",
                "iTotalPlay": "1.7万",
                "iMark": "0",
                "sExt1": "585,898,948,895,1281",
                "sExt2": "",
                "sExt3": "",
                "sIdxTime": "2017-04-17 14:34:35",
                "sCreated": "2017-04-17 14:34:35",
                "iBiz": "18"
            },
            {
                "iVideoId": "120129",
                "iType": "616",
                "iSubType": "636",
                "sAuthor": "TGL",
                "iFrom": "1",
                "sTitle": "最强法坦实力输出 东皇太一击杀集锦",
                "sDesc": "野蛮法师诸葛亮峡谷死神输出机器；剑仙李白十步杀一人千里不留行；神医扁鹊能救人能能杀人；高爆发兰陵王屠杀起来毫不手软；最强法坦实力输出东皇太一",
                "sUrl": "",
                "sIMG": "//itea-cdn.qq.com/file/tgl/20170417/1.1492366848.jpg",
                "iTime": "03:18",
                "iTotalPlay": "1.5万",
                "iMark": "0",
                "sExt1": "589,902,895,2377,2314",
                "sExt2": "",
                "sExt3": "",
                "sIdxTime": "2017-04-17 14:28:06",
                "sCreated": "2017-04-17 14:28:06",
                "iBiz": "18"
            },
            {
                "iVideoId": "120130",
                "iType": "616",
                "iSubType": "636",
                "sAuthor": "TGL",
                "iFrom": "1",
                "sTitle": "骚走位强输出能抗能打 宫本武藏击杀秀",
                "sDesc": "鲜血枭雄曹操大开杀戒势不可挡；杨戬逆转乾坤走位秀屠杀；勇者无惧虞姬双枪劲射不怂就是刚；长枪在手天下我有赵云；骚走位强输出能抗能打宫本武藏",
                "sUrl": "",
                "sIMG": "//itea-cdn.qq.com/file/tgl/20170417/2.1492367010.jpg",
                "iTime": "03:25",
                "iTotalPlay": "8498",
                "iMark": "0",
                "sExt1": "590,598,620,948,1638",
                "sExt2": "",
                "sExt3": "",
                "sIdxTime": "2017-04-17 14:28:05",
                "sCreated": "2017-04-17 14:28:05",
                "iBiz": "18"
            },
            {
                "iVideoId": "120131",
                "iType": "616",
                "iSubType": "636",
                "sAuthor": "TGL",
                "iFrom": "1",
                "sTitle": "敢打敢拼就是这么猛 诸葛亮精彩击杀秀",
                "sDesc": "鹰击长空娜可露露笑傲王者峡谷；大长腿双枪虞姬打人就是射；潇洒走位实力输出马可波罗；走位输出实力乱射鲁班七号；敢打敢拼就是这么猛诸葛亮",
                "sUrl": "",
                "sIMG": "//itea-cdn.qq.com/file/tgl/20170417/4.1492367438.jpg",
                "iTime": "03:05",
                "iTotalPlay": "8336",
                "iMark": "0",
                "sExt1": "606,898,948,1240,2314",
                "sExt2": "",
                "sExt3": "",
                "sIdxTime": "2017-04-17 14:28:03",
                "sCreated": "2017-04-17 14:28:03",
                "iBiz": "18"
            },
            {
                "iVideoId": "119903",
                "iType": "616",
                "iSubType": "636",
                "sAuthor": "TGL",
                "iFrom": "1",
                "sTitle": "团战收割机峡谷杀神 荆轲炫酷操作秀",
                "sDesc": "刘备新一代的站撸王者就是刚；公务武藏天下无双空明斩实力屠杀；草原上的雄鹰峡谷中的王者成吉思汗；关羽刀锋铁骑我的大刀突破天际；团战收割机峡谷杀神荆轲",
                "sUrl": "",
                "sIMG": "//itea-cdn.qq.com/file/tgl/20170416/3.1492286492.jpg",
                "iTime": "03:09",
                "iTotalPlay": "4338",
                "iMark": "0",
                "sExt1": "598,602,892,1175,1281",
                "sExt2": "",
                "sExt3": "",
                "sIdxTime": "2017-04-16 15:23:50",
                "sCreated": "2017-04-16 15:23:50",
                "iBiz": "18"
            },
            {
                "iVideoId": "119914",
                "iType": "616",
                "iSubType": "636",
                "sAuthor": "TGL",
                "iFrom": "1",
                "sTitle": "天下无双霸气空明斩 宫本武藏精彩击杀秀",
                "sDesc": "鲁班七号超高伤害怒取三杀；霸气收割表演时刻高渐离；遇见就是干最秀射手马可波罗；虞姬双击劲射收残血看谁还敢浪；天下无双霸气空明斩宫本武藏",
                "sUrl": "",
                "sIMG": "//itea-cdn.qq.com/file/tgl/20170416/1.1492285372.jpg",
                "iTime": "03:06",
                "iTotalPlay": "3556",
                "iMark": "0",
                "sExt1": "597,598,606,948,1240",
                "sExt2": "",
                "sExt3": "",
                "sIdxTime": "2017-04-16 15:22:01",
                "sCreated": "2017-04-16 15:22:01",
                "iBiz": "18"
            },
            {
                "iVideoId": "119915",
                "iType": "616",
                "iSubType": "636",
                "sAuthor": "TGL",
                "iFrom": "1",
                "sTitle": "死亡摇滚致命乐章 高渐离击杀操作秀",
                "sDesc": "马可波罗走位输出怒取三杀；韩信不怂硬怼上去就是刚；成吉思汗无坚不摧屠杀实力秀；走位输出实力乱射鲁班七号；死亡摇滚致命乐章高渐离",
                "sUrl": "",
                "sIMG": "//itea-cdn.qq.com/file/tgl/20170416/3.1492285527.jpg",
                "iTime": "02:56",
                "iTotalPlay": "3071",
                "iMark": "0",
                "sExt1": "597,599,606,1240,1281",
                "sExt2": "",
                "sExt3": "",
                "sIdxTime": "2017-04-16 15:22:00",
                "sCreated": "2017-04-16 15:22:00",
                "iBiz": "18"
            },
            {
                "iVideoId": "119916",
                "iType": "616",
                "iSubType": "636",
                "sAuthor": "TGL",
                "iFrom": "1",
                "sTitle": "刀锋铁骑所向披靡 关羽击杀top5",
                "sDesc": "成吉思汗走位秀操作怒取三杀；大橘子浪人之道屠杀之道；韩信一杆长枪让你感受被支配的恐惧；马可波罗激情四射玩的就是心跳；刀锋铁骑所向披靡关羽",
                "sUrl": "",
                "sIMG": "//itea-cdn.qq.com/file/tgl/20170416/2.1492285644.jpg",
                "iTime": "03:21",
                "iTotalPlay": "4158",
                "iMark": "0",
                "sExt1": "599,1175,1240,1253,1281",
                "sExt2": "",
                "sExt3": "",
                "sIdxTime": "2017-04-16 15:21:59",
                "sCreated": "2017-04-16 15:21:59",
                "iBiz": "18"
            }
        ],
        "total": "2511",
        "pagesize": "10",
        "totalpage": "252",
        "page": "2"
    }
}